Metadata-Version: 2.1
Name: isom600
Version: 0.1
Summary: Toolbox for ISOM2600 
